LICENSE.txt
MANIFEST.in
README.rst
setup.cfg
setup.py
rest_framework_simplejwt/__init__.py
rest_framework_simplejwt/authentication.py
rest_framework_simplejwt/backends.py
rest_framework_simplejwt/compat.py
rest_framework_simplejwt/exceptions.py
rest_framework_simplejwt/models.py
rest_framework_simplejwt/serializers.py
rest_framework_simplejwt/settings.py
rest_framework_simplejwt/state.py
rest_framework_simplejwt/tokens.py
rest_framework_simplejwt/utils.py
rest_framework_simplejwt/views.py
rest_framework_simplejwt/locale/cs/LC_MESSAGES/django.mo
rest_framework_simplejwt/locale/cs/LC_MESSAGES/django.po
rest_framework_simplejwt/locale/de_CH/LC_MESSAGES/django.mo
rest_framework_simplejwt/locale/de_CH/LC_MESSAGES/django.po
rest_framework_simplejwt/locale/es/LC_MESSAGES/django.mo
rest_framework_simplejwt/locale/es/LC_MESSAGES/django.po
rest_framework_simplejwt/locale/es_AR/LC_MESSAGES/django.mo
rest_framework_simplejwt/locale/es_AR/LC_MESSAGES/django.po
rest_framework_simplejwt/locale/es_CL/LC_MESSAGES/django.mo
rest_framework_simplejwt/locale/es_CL/LC_MESSAGES/django.po
rest_framework_simplejwt/locale/fa_IR/LC_MESSAGES/django.mo
rest_framework_simplejwt/locale/fa_IR/LC_MESSAGES/django.po
rest_framework_simplejwt/locale/fr/LC_MESSAGES/django.mo
rest_framework_simplejwt/locale/fr/LC_MESSAGES/django.po
rest_framework_simplejwt/locale/id_ID/LC_MESSAGES/django.mo
rest_framework_simplejwt/locale/id_ID/LC_MESSAGES/django.po
rest_framework_simplejwt/locale/it_IT/LC_MESSAGES/django.mo
rest_framework_simplejwt/locale/it_IT/LC_MESSAGES/django.po
rest_framework_simplejwt/locale/ko_KR/LC_MESSAGES/django.mo
rest_framework_simplejwt/locale/ko_KR/LC_MESSAGES/django.po
rest_framework_simplejwt/locale/nl_NL/LC_MESSAGES/django.mo
rest_framework_simplejwt/locale/nl_NL/LC_MESSAGES/django.po
rest_framework_simplejwt/locale/pl_PL/LC_MESSAGES/django.mo
rest_framework_simplejwt/locale/pl_PL/LC_MESSAGES/django.po
rest_framework_simplejwt/locale/pt_BR/LC_MESSAGES/django.mo
rflow_djangorestframework_simplejwt.egg-info/PKG-INFO
rflow_djangorestframework_simplejwt.egg-info/SOURCES.txt
rflow_djangorestframework_simplejwt.egg-info/dependency_links.txt
rflow_djangorestframework_simplejwt.egg-info/not-zip-safe
rflow_djangorestframework_simplejwt.egg-info/requires.txt
rflow_djangorestframework_simplejwt.egg-info/top_level.txt
