Metadata-Version: 2.1
Name: rflow-djangorestframework-simplejwt
Version: 5.1.0
Summary: A minimal JSON Web Token authentication plugin for Django REST Framework
Home-page: https://github.com/jazzband/djangorestframework-simplejwt
Author: David Sanders
Author-email: davesque@gmail.com
License: MIT
Platform: UNKNOWN
Classifier: Development Status :: 5 - Production/Stable
Classifier: Environment :: Web Environment
Classifier: Framework :: Django
Classifier: Framework :: Django :: 2.2
Classifier: Framework :: Django :: 3.2
Classifier: Framework :: Django :: 4.0
Classifier: Intended Audience :: Developers
Classifier: License :: OSI Approved :: MIT License
Classifier: Operating System :: OS Independent
Classifier: Programming Language :: Python
Classifier: Programming Language :: Python :: 3
Classifier: Programming Language :: Python :: 3.7
Classifier: Programming Language :: Python :: 3.8
Classifier: Programming Language :: Python :: 3.9
Classifier: Programming Language :: Python :: 3.10
Classifier: Topic :: Internet :: WWW/HTTP
Requires-Python: >=3.7
Provides-Extra: test
Provides-Extra: lint
Provides-Extra: doc
Provides-Extra: dev
Provides-Extra: python-jose
License-File: LICENSE.txt
